vss.py
vssapi-0.0.2.dist-info/LICENSE
vssapi-0.0.2.dist-info/METADATA
vssapi-0.0.2.dist-info/WHEEL
vssapi-0.0.2.dist-info/top_level.txt
vssapi-0.0.2.dist-info/RECORD
