Metadata-Version: 2.1
Name: vssapi
Version: 0.0.2
Summary: VSS API package
Home-page: UNKNOWN
Author: Jure Jancigaj
Author-email: falcon2k16@gmail.com
License: UNKNOWN
Keywords: vss
Platform: UNKNOWN
Classifier: Development Status :: 3 - Alpha
Classifier: Intended Audience :: Developers
Classifier: Topic :: Software Development :: Libraries :: Python Modules
Classifier: License :: OSI Approved :: MIT License
Classifier: Operating System :: OS Independent
Classifier: Programming Language :: Python :: 3 :: Only
Classifier: Programming Language :: Python :: 3.6
License-File: LICENSE
Requires-Dist: requests
Requires-Dist: requests-toolbelt
Requires-Dist: python-dotenv
